MANIFEST.in
README.txt
setup.cfg
setup.py
atreal/__init__.py
atreal.filestorage.blobfile.egg-info/PKG-INFO
atreal.filestorage.blobfile.egg-info/SOURCES.txt
atreal.filestorage.blobfile.egg-info/dependency_links.txt
atreal.filestorage.blobfile.egg-info/entry_points.txt
atreal.filestorage.blobfile.egg-info/namespace_packages.txt
atreal.filestorage.blobfile.egg-info/not-zip-safe
atreal.filestorage.blobfile.egg-info/requires.txt
atreal.filestorage.blobfile.egg-info/top_level.txt
atreal/filestorage/__init__.py
atreal/filestorage/blobfile/__init__.py
atreal/filestorage/blobfile/configure.zcml
atreal/filestorage/blobfile/fs.py
atreal/filestorage/blobfile/interfaces.py
atreal/filestorage/blobfile/store.py
atreal/filestorage/blobfile/tests.py
atreal/filestorage/blobfile/version.txt