Metadata-Version: 1.0
Name: atreal.filestorage.blobfile
Version: 1.0.0rc1
Summary: Defines a common API to handle file objects independently of storage - Blobfile plugin
Home-page: http://www.atreal.net/
Author: atReal
Author-email: contact@atreal.net
License: GPL
Keywords: plone atreal file blob blobfile
Platform: UNKNOWN
Classifier: Framework :: Plone
Classifier: Programming Language :: Python
Classifier: Topic :: Software Development :: Libraries :: Python Modules
